{
  "receipt_id": "eddcdec6-057f-42d0-8a91-5ad178a76cd6",
  "protocol_version": 1,
  "security_mode": "GatewayOnly",
  "enclave_measurements": {
    "pcr0": [
      170,
      170,
      170,
      170,
      170,
      170,
      170,
      170,
      170,
      170,
      170,
      170,
      170,
      170,
      170,
      170,
      170,
      170,
      170,
      170,
      170,
      170,
      170,
      170,
      170,
      170,
      170,
      170,
      170,
      170,
      170,
      170,
      170,
      170,
      170,
      170,
      170,
      170,
      170,
      170,
      170,
      170,
      170,
      170,
      170,
      170,
      170,
      170
    ],
    "pcr1": [
      187,
      187,
      187,
      187,
      187,
      187,
      187,
      187,
      187,
      187,
      187,
      187,
      187,
      187,
      187,
      187,
      187,
      187,
      187,
      187,
      187,
      187,
      187,
      187,
      187,
      187,
      187,
      187,
      187,
      187,
      187,
      187,
      187,
      187,
      187,
      187,
      187,
      187,
      187,
      187,
      187,
      187,
      187,
      187,
      187,
      187,
      187,
      187
    ],
    "pcr2": [
      204,
      204,
      204,
      204,
      204,
      204,
      204,
      204,
      204,
      204,
      204,
      204,
      204,
      204,
      204,
      204,
      204,
      204,
      204,
      204,
      204,
      204,
      204,
      204,
      204,
      204,
      204,
      204,
      204,
      204,
      204,
      204,
      204,
      204,
      204,
      204,
      204,
      204,
      204,
      204,
      204,
      204,
      204,
      204,
      204,
      204,
      204,
      204
    ],
    "pcr8": null,
    "measurement_type": "tdx-mrtd-rtmr"
  },
  "attestation_doc_hash": [
    36,
    234,
    20,
    229,
    23,
    15,
    86,
    247,
    113,
    250,
    11,
    176,
    113,
    227,
    134,
    14,
    229,
    61,
    163,
    73,
    125,
    94,
    226,
    156,
    132,
    24,
    138,
    245,
    167,
    54,
    101,
    114
  ],
  "request_hash": [
    225,
    147,
    235,
    158,
    180,
    67,
    240,
    157,
    84,
    162,
    145,
    10,
    144,
    207,
    98,
    84,
    212,
    5,
    121,
    229,
    84,
    38,
    18,
    245,
    49,
    167,
    126,
    241,
    22,
    136,
    45,
    66
  ],
  "response_hash": [
    55,
    175,
    210,
    2,
    179,
    79,
    132,
    188,
    207,
    117,
    155,
    175,
    110,
    158,
    114,
    14,
    66,
    132,
    152,
    168,
    239,
    122,
    222,
    140,
    56,
    28,
    61,
    58,
    7,
    18,
    237,
    65
  ],
  "policy_version": "v1-default",
  "sequence_number": 199,
  "execution_timestamp": 1771532424,
  "model_id": "stage-0",
  "model_version": "1.0",
  "execution_time_ms": 64,
  "memory_peak_mb": 0,
  "signature": [
    69,
    240,
    67,
    233,
    56,
    169,
    235,
    127,
    87,
    115,
    160,
    155,
    199,
    121,
    219,
    114,
    224,
    239,
    137,
    89,
    198,
    140,
    246,
    96,
    117,
    124,
    209,
    84,
    73,
    244,
    220,
    192,
    97,
    49,
    248,
    119,
    154,
    112,
    187,
    212,
    70,
    240,
    237,
    194,
    138,
    44,
    215,
    163,
    173,
    212,
    141,
    58,
    162,
    6,
    33,
    95,
    8,
    160,
    167,
    207,
    223,
    91,
    213,
    7
  ],
  "destroy_evidence": {
    "timestamp": 1771532424,
    "actions": [
      {
        "target": "output_bytes",
        "mechanism": "explicit_zeroize"
      },
      {
        "target": "output_tensor",
        "mechanism": "explicit_zeroize"
      },
      {
        "target": "generated_text",
        "mechanism": "explicit_zeroize"
      },
      {
        "target": "session_dek",
        "mechanism": "drop_on_scope_exit"
      },
      {
        "target": "ephemeral_keypair",
        "mechanism": "drop_on_scope_exit"
      }
    ]
  }
}